aivol/__init__.py
aivol/compare.py
aivol/config.py
aivol/experiment.py
aivol/resolve.py
aivol/sidecar.py
aivol-0.0.7.dist-info/LICENSE
aivol-0.0.7.dist-info/METADATA
aivol-0.0.7.dist-info/WHEEL
aivol-0.0.7.dist-info/top_level.txt
aivol-0.0.7.dist-info/RECORD
