Metadata-Version: 2.1
Name: aivol
Version: 0.0.7
Summary: Utilities for AI volumes
Author-email: Dmitry Galchinsky <galchinsky@borisfx.com>
License: MIT License
Classifier: Programming Language :: Python :: 3
Classifier: License :: OSI Approved :: MIT License
Classifier: Operating System :: OS Independent
License-File: LICENSE
Requires-Dist: PyYAML >=5.4
Requires-Dist: pandas >=1.1
